pyEPVis.py
pyEPVis-0.0.4.dist-info/LICENSE
pyEPVis-0.0.4.dist-info/METADATA
pyEPVis-0.0.4.dist-info/WHEEL
pyEPVis-0.0.4.dist-info/top_level.txt
pyEPVis-0.0.4.dist-info/RECORD
