Metadata-Version: 2.1
Name: pyEPVis
Version: 0.0.4
Summary: A Expression and Particle movement visualizer package
Home-page: https://github.com/AAbhijithA/pyEPVis
Author: Abhijith Ajith
Keywords: particle,expression,expression visualizer,particle movement,visualizer,animation
Classifier: Programming Language :: Python :: 3
Classifier: License :: OSI Approved :: MIT License
Classifier: Operating System :: OS Independent
Requires-Python: >=3.9.2
License-File: LICENSE
Requires-Dist: numpy
Requires-Dist: plotly
